gaurabda/GCAyanamsha.py
gaurabda/GCCalendar.py
gaurabda/GCCalendarDay.py
gaurabda/GCConjunction.py
gaurabda/GCCoords.py
gaurabda/GCCountry.py
gaurabda/GCDayData.py
gaurabda/GCDisplaySettings.py
gaurabda/GCEarthData.py
gaurabda/GCEvent.py
gaurabda/GCEventList.py
gaurabda/GCGlobal.py
gaurabda/GCGregorianDate.py
gaurabda/GCLayoutData.py
gaurabda/GCLocation.py
gaurabda/GCLocationList.py
gaurabda/GCMath.py
gaurabda/GCMoonData.py
gaurabda/GCNaksatra.py
gaurabda/GCPancangaDate.py
gaurabda/GCRasi.py
gaurabda/GCSankranti.py
gaurabda/GCStringBuilder.py
gaurabda/GCStrings.py
gaurabda/GCSunData.py
gaurabda/GCTime.py
gaurabda/GCTimeZone.py
gaurabda/GCTithi.py
gaurabda/GCUT.py
gaurabda/GCYoga.py
gaurabda/Server.py
gaurabda/TAppDay.py
gaurabda/TCalendar.py
gaurabda/TCoreEvents.py
gaurabda/TMasaList.py
gaurabda/TServer.py
gaurabda/TToday.py
gaurabda/__init__.py
gaurabda/utest.py
gaurabda/GCEnums/CaturmasyaCodes.py
gaurabda/GCEnums/CoreEventType.py
gaurabda/GCEnums/DisplayPriorities.py
gaurabda/GCEnums/EkadasiParanaType.py
gaurabda/GCEnums/FastType.py
gaurabda/GCEnums/FeastType.py
gaurabda/GCEnums/GCDS.py
gaurabda/GCEnums/GlobalStringsEnum.py
gaurabda/GCEnums/KalaType.py
gaurabda/GCEnums/MahadvadasiType.py
gaurabda/GCEnums/MainFrameContentType.py
gaurabda/GCEnums/MasaId.py
gaurabda/GCEnums/NaksatraId.py
gaurabda/GCEnums/PaksaId.py
gaurabda/GCEnums/SankrantiId.py
gaurabda/GCEnums/SpecialFestivalId.py
gaurabda/GCEnums/TithiId.py
gaurabda/GCEnums/WeekDayId.py
gaurabda/GCEnums/__init__.py
gaurabda/res/countries.json
gaurabda/res/eventfast.json
gaurabda/res/events.json
gaurabda/res/locations.json
gaurabda/res/rtf_color_table.txt
gaurabda/res/strings.json
gaurabda/res/timezones.json
gaurabda-0.8.4.dist-info/LICENSE
gaurabda-0.8.4.dist-info/METADATA
gaurabda-0.8.4.dist-info/WHEEL
gaurabda-0.8.4.dist-info/top_level.txt
gaurabda-0.8.4.dist-info/RECORD
