Metadata-Version: 2.1
Name: gaurabda
Version: 0.8.4
Summary: Calculation of Gaurabda calendar (Gaudiya Vaishnava calendar)
Home-page: https://github.com/gopa810/gaurabda-calendar
Author: Gopal
Author-email: root@gopal.home.sk
License: MIT
Download-URL: https://github.com/gopa810/gaurabda-calendar/archive/0.8.4.tar.gz
Keywords: gaurabda,vaisnava,vaishnava,ISKCON,GCAL
Platform: UNKNOWN
Classifier: Development Status :: 4 - Beta
Classifier: Programming Language :: Python :: 3
Classifier: Intended Audience :: Developers
Classifier: License :: OSI Approved :: MIT License
Classifier: Operating System :: OS Independent
Classifier: Topic :: Software Development :: Build Tools
Requires-Python: >=3.4
